fybrik_python_logging/__init__.py
fybrik_python_logging-0.1.0.dist-info/METADATA
fybrik_python_logging-0.1.0.dist-info/WHEEL
fybrik_python_logging-0.1.0.dist-info/top_level.txt
fybrik_python_logging-0.1.0.dist-info/RECORD
