Metadata-Version: 2.1
Name: fybrik-python-logging
Version: 0.1.0
Summary: Python Logging Package for Fybrik Components
Home-page: https://github.com/fybrik/fybrik/tree/master/python/logging
Author: FybrikUser
Author-email: FybrikUser@il.ibm.com
License: Apache License, Version 2.0
Platform: UNKNOWN
Requires-Dist: JSON-log-formatter (==0.5.0)
